mkdocs_build_plantuml_plugin/__init__.py
mkdocs_build_plantuml_plugin/plantuml.py
mkdocs_build_plantuml_plugin-1.11.0.dist-info/LICENSE
mkdocs_build_plantuml_plugin-1.11.0.dist-info/METADATA
mkdocs_build_plantuml_plugin-1.11.0.dist-info/WHEEL
mkdocs_build_plantuml_plugin-1.11.0.dist-info/entry_points.txt
mkdocs_build_plantuml_plugin-1.11.0.dist-info/top_level.txt
mkdocs_build_plantuml_plugin-1.11.0.dist-info/RECORD
